README.md
setup.cfg
setup.py
certifi/__init__.py
certifi/__main__.py
certifi/core.py
chardet/__init__.py
chardet/big5freq.py
chardet/big5prober.py
chardet/chardistribution.py
chardet/charsetgroupprober.py
chardet/charsetprober.py
chardet/codingstatemachine.py
chardet/compat.py
chardet/cp949prober.py
chardet/enums.py
chardet/escprober.py
chardet/escsm.py
chardet/eucjpprober.py
chardet/euckrfreq.py
chardet/euckrprober.py
chardet/euctwfreq.py
chardet/euctwprober.py
chardet/gb2312freq.py
chardet/gb2312prober.py
chardet/hebrewprober.py
chardet/jisfreq.py
chardet/jpcntx.py
chardet/langbulgarianmodel.py
chardet/langcyrillicmodel.py
chardet/langgreekmodel.py
chardet/langhebrewmodel.py
chardet/langhungarianmodel.py
chardet/langthaimodel.py
chardet/langturkishmodel.py
chardet/latin1prober.py
chardet/mbcharsetprober.py
chardet/mbcsgroupprober.py
chardet/mbcssm.py
chardet/sbcharsetprober.py
chardet/sbcsgroupprober.py
chardet/sjisprober.py
chardet/universaldetector.py
chardet/utf8prober.py
chardet/version.py
chardet/cli/__init__.py
chardet/cli/chardetect.py
idna/__init__.py
idna/codec.py
idna/compat.py
idna/core.py
idna/idnadata.py
idna/intranges.py
idna/package_data.py
idna/uts46data.py
py_antilibrary/__init__.py
py_antilibrary.egg-info/PKG-INFO
py_antilibrary.egg-info/SOURCES.txt
py_antilibrary.egg-info/dependency_links.txt
py_antilibrary.egg-info/not-zip-safe
py_antilibrary.egg-info/requires.txt
py_antilibrary.egg-info/top_level.txt
requests/__init__.py
requests/__version__.py
requests/_internal_utils.py
requests/adapters.py
requests/api.py
requests/auth.py
requests/certs.py
requests/compat.py
requests/cookies.py
requests/exceptions.py
requests/help.py
requests/hooks.py
requests/models.py
requests/packages.py
requests/sessions.py
requests/status_codes.py
requests/structures.py
requests/utils.py
urllib3/__init__.py
urllib3/_collections.py
urllib3/connection.py
urllib3/connectionpool.py
urllib3/exceptions.py
urllib3/fields.py
urllib3/filepost.py
urllib3/poolmanager.py
urllib3/request.py
urllib3/response.py
urllib3/contrib/__init__.py
urllib3/contrib/_appengine_environ.py
urllib3/contrib/appengine.py
urllib3/contrib/ntlmpool.py
urllib3/contrib/pyopenssl.py
urllib3/contrib/securetransport.py
